cognite/__init__.py
cognite/databricks_utils/__init__.py
cognite/databricks_utils/cli.py
cognite/databricks_utils/file_util.py
cognite/databricks_utils/jobs.py
cognite/databricks_utils/scopes.py
cognite/databricks_utils/users.py
cognite_databricks_utils-1.0.0.dist-info/entry_points.txt
cognite_databricks_utils-1.0.0.dist-info/WHEEL
cognite_databricks_utils-1.0.0.dist-info/METADATA
cognite_databricks_utils-1.0.0.dist-info/RECORD
