Metadata-Version: 2.1
Name: cognite-databricks-utils
Version: 1.0.0
Summary: Utilities for administrating a Databricks shard
Author: Magnus Moan
Author-email: magnus.moan@cognite.com
Requires-Python: >=3.7,<4.0
Classifier: Programming Language :: Python :: 3
Classifier: Programming Language :: Python :: 3.7
Classifier: Programming Language :: Python :: 3.8
Requires-Dist: click (>=7.1.1,<8.0.0)
Requires-Dist: databricks-api (>=0.4.0,<0.5.0)
Requires-Dist: python-semantic-release (>=6.0.1,<7.0.0)
Requires-Dist: xlrd (>=1.2.0,<2.0.0)
